{
  "title": "Commute Load Generator",
  "uid": "commute-load",
  "schemaVersion": 39,
  "version": 1,
  "refresh": "10s",
  "time": {
    "from": "now-15m",
    "to": "now"
  },
  "templating": {
    "list": [
      {
        "name": "datasource",
        "label": "Data source",
        "type": "datasource",
        "query": "prometheus",
        "refresh": 1,
        "includeAll": false,
        "multi": false,
        "sort": 0
      },
      {
        "name": "region",
        "label": "Region",
        "type": "query",
        "datasource": {
          "type": "prometheus",
          "uid": "${datasource}"
        },
        "query": "label_values(request_seconds_count, region)",
        "refresh": 2,
        "includeAll": true,
        "allValue": ".*",
        "multi": true,
        "current": {},
        "sort": 1
      },
      {
        "name": "instance",
        "label": "Instance",
        "type": "query",
        "datasource": {
          "type": "prometheus",
          "uid": "${datasource}"
        },
        "query": "label_values(request_seconds_count{region=~\"$region\"}, instance)",
        "refresh": 2,
        "includeAll": true,
        "allValue": ".*",
        "multi": true,
        "current": {},
        "sort": 1
      }
    ]
  },
  "panels": [
    {
      "id": 3,
      "title": "Load generator request rate",
      "type": "timeseries",
      "gridPos": {
        "h": 8,
        "w": 24,
        "x": 0,
        "y": 0
      },
      "datasource": {
        "type": "prometheus",
        "uid": "${datasource}"
      },
      "targets": [
        {
          "expr": "sum(rate(request_seconds_count{region=~\"$region\",instance=~\"$instance\"}[$__rate_interval]))",
          "legendFormat": "requests/s",
          "refId": "A"
        }
      ],
      "fieldConfig": {
        "defaults": {
          "unit": "reqps",
          "custom": {
            "fillOpacity": 20,
            "lineWidth": 2,
            "gradientMode": "none"
          },
          "color": {
            "mode": "palette-classic"
          }
        }
      },
      "options": {
        "tooltip": {
          "mode": "multi",
          "sort": "none"
        },
        "legend": {
          "displayMode": "list",
          "placement": "bottom"
        }
      }
    },
    {
      "id": 4,
      "title": "Load generator latency percentiles (client-side)",
      "type": "timeseries",
      "gridPos": {
        "h": 8,
        "w": 24,
        "x": 0,
        "y": 8
      },
      "datasource": {
        "type": "prometheus",
        "uid": "${datasource}"
      },
      "targets": [
        {
          "expr": "histogram_quantile(0.50, sum by (le) (rate(request_seconds_bucket{region=~\"$region\",instance=~\"$instance\"}[$__rate_interval])))",
          "legendFormat": "p50",
          "refId": "A"
        },
        {
          "expr": "histogram_quantile(0.95, sum by (le) (rate(request_seconds_bucket{region=~\"$region\",instance=~\"$instance\"}[$__rate_interval])))",
          "legendFormat": "p95",
          "refId": "B"
        },
        {
          "expr": "histogram_quantile(0.99, sum by (le) (rate(request_seconds_bucket{region=~\"$region\",instance=~\"$instance\"}[$__rate_interval])))",
          "legendFormat": "p99",
          "refId": "C"
        }
      ],
      "fieldConfig": {
        "defaults": {
          "unit": "s",
          "custom": {
            "fillOpacity": 10,
            "lineWidth": 2,
            "gradientMode": "none"
          },
          "color": {
            "mode": "palette-classic"
          }
        }
      },
      "options": {
        "tooltip": {
          "mode": "multi",
          "sort": "none"
        },
        "legend": {
          "displayMode": "list",
          "placement": "bottom"
        }
      }
    }
  ]
}
